main.py
siglip2_embedder_api-1.4.3.dist-info/licenses/LICENSE
siglip2_embedder_api-1.4.3.dist-info/METADATA
siglip2_embedder_api-1.4.3.dist-info/WHEEL
siglip2_embedder_api-1.4.3.dist-info/entry_points.txt
siglip2_embedder_api-1.4.3.dist-info/top_level.txt
siglip2_embedder_api-1.4.3.dist-info/RECORD
