Metadata-Version: 2.4
Name: siglip2-embedder-api
Version: 1.4.3
Summary: A microservice with FastAPI to generate embeddings with SigLIP 2
Author-email: Yudivián Almeida Cruz <yudivian@email.com>
License-Expression: MIT
Project-URL: Homepage, https://github.com/yudivian/siglip2-embedder
Project-URL: Issues, https://github.com/yudivian/siglip2-embedder/issues
Requires-Python: >=3.8
License-File: LICENSE
Requires-Dist: torch>=2.1.0
Requires-Dist: transformers>=4.40.0
Requires-Dist: numpy>=1.24.0
Requires-Dist: Pillow>=10.0.0
Requires-Dist: PyYAML>=6.0
Requires-Dist: fastapi>=0.104.0
Requires-Dist: uvicorn[standard]>=0.23.0
Requires-Dist: python-multipart>=0.0.6
Dynamic: license-file
